sqlml_parser/__init__.py
sqlml_parser/format/__init__.py
sqlml_parser/format/formatter.py
sqlml_parser/parser/__init__.py
sqlml_parser/parser/exceptions.py
sqlml_parser/parser/parser_utils.py
sqlml_parser/parser/mysql_parser/__init__.py
sqlml_parser/parser/mysql_parser/lexer.py
sqlml_parser/parser/mysql_parser/parser.py
sqlml_parser/parser/mysql_parser/parser_table.py
sqlml_parser/parser/mysql_parser/reserved.py
sqlml_parser/parser/oceanbase_parser/__init__.py
sqlml_parser/parser/oceanbase_parser/lexer.py
sqlml_parser/parser/oceanbase_parser/parser.py
sqlml_parser/parser/oceanbase_parser/parser_table.py
sqlml_parser/parser/oceanbase_parser/reserved.py
sqlml_parser/parser/odps_parser/__init__.py
sqlml_parser/parser/odps_parser/lexer.py
sqlml_parser/parser/odps_parser/parser.py
sqlml_parser/parser/odps_parser/parser_table.py
sqlml_parser/parser/odps_parser/reserved.py
sqlml_parser/parser/tree/__init__.py
sqlml_parser/parser/tree/approximate.py
sqlml_parser/parser/tree/call_argument.py
sqlml_parser/parser/tree/explain.py
sqlml_parser/parser/tree/expression.py
sqlml_parser/parser/tree/field_type.py
sqlml_parser/parser/tree/grouping.py
sqlml_parser/parser/tree/index_type.py
sqlml_parser/parser/tree/join_criteria.py
sqlml_parser/parser/tree/literal.py
sqlml_parser/parser/tree/node.py
sqlml_parser/parser/tree/qualified_name.py
sqlml_parser/parser/tree/query_specification.py
sqlml_parser/parser/tree/relation.py
sqlml_parser/parser/tree/rewrite.py
sqlml_parser/parser/tree/select.py
sqlml_parser/parser/tree/select_item.py
sqlml_parser/parser/tree/set_operation.py
sqlml_parser/parser/tree/sort_item.py
sqlml_parser/parser/tree/statement.py
sqlml_parser/parser/tree/table.py
sqlml_parser/parser/tree/table_element.py
sqlml_parser/parser/tree/transaction.py
sqlml_parser/parser/tree/values.py
sqlml_parser/parser/tree/visitor.py
sqlml_parser/parser/tree/window.py
sqlml_parser/parser/tree/with_stmt.py
sqlml_parser-0.0.1.dist-info/WHEEL
sqlml_parser-0.0.1.dist-info/METADATA
sqlml_parser-0.0.1.dist-info/RECORD
