Metadata-Version: 2.1
Name: sqlml-parser
Version: 0.0.1
Summary: A sql parser which support mysql, oceanbase and odps
Author-email: khulnasoft-bot <inrfo@khulnasoft.com>
Requires-Python: >=3.7
Classifier: Programming Language :: Python :: 3
Classifier: License :: OSI Approved :: Apache Software License
Classifier: Operating System :: OS Independent
Requires-Dist: ply == 3.11
Project-URL: Bug Tracker, https://github.com/khulnasoft-lab/sqlml-parser/issues
Project-URL: Homepage, https://github.com/khulnasoft-lab/sqlml-parser
